isp_tensors/__init__.py
isp_tensors/main.py
isp_tensors/utils.py
isp_tensors-0.0.1.dist-info/LICENSE
isp_tensors-0.0.1.dist-info/METADATA
isp_tensors-0.0.1.dist-info/WHEEL
isp_tensors-0.0.1.dist-info/RECORD
