Metadata-Version: 2.1
Name: isp_tensors
Version: 0.0.1
Summary: This is a template repository for Python projects that use Poetry for their dependency management.
Home-page: https://github.com/csaybar/isp-tensors
Author: Cesar Aybar
Author-email: fcesaraybar@uv.es
Requires-Python: >=3.8,<4.0
Classifier: Programming Language :: Python :: 3
Classifier: Programming Language :: Python :: 3.8
Classifier: Programming Language :: Python :: 3.9
Classifier: Programming Language :: Python :: 3.10
Classifier: Programming Language :: Python :: 3.11
Requires-Dist: safetensors (>=0.4.0,<0.5.0)
Project-URL: Documentation, https://csaybar.github.io/isp-tensors/
Project-URL: Repository, https://github.com/csaybar/isp-tensors
